polar_vortex/interfaces/.gitignore
polar_vortex/interfaces/log_interface.py
polar_vortex/interfaces/polar_interface.py
polar_vortex/interfaces/vortex_interface.py
polar_vortex/models/__init__.py
polar_vortex/models/polar_model.py
polar_vortex/protocols/__init__.py
polar_vortex/protocols/database_protocols.py
polar_vortex/pv_tool.py
polar_vortex-0.1.3.dist-info/LICENSE
polar_vortex-0.1.3.dist-info/METADATA
polar_vortex-0.1.3.dist-info/WHEEL
polar_vortex-0.1.3.dist-info/entry_points.txt
polar_vortex-0.1.3.dist-info/RECORD
