Metadata-Version: 2.1
Name: polar-vortex
Version: 0.1.3
Summary: Polar Vortex is column store database that uses Polars dataframes and either CSV or Parquet as the underlying storag
License: Apache 2.0
Author: daniel-davee
Author-email: daniel.v.davee@gmail.com
Requires-Python: >=3.8,<4.0
Classifier: License :: Other/Proprietary License
Classifier: Programming Language :: Python :: 3
Classifier: Programming Language :: Python :: 3.8
Classifier: Programming Language :: Python :: 3.9
Classifier: Programming Language :: Python :: 3.10
Classifier: Programming Language :: Python :: 3.11
Requires-Dist: candy-wrapper (>=1.0.1,<2.0.0)
Requires-Dist: magic-run-cmd (>=1.1.0,<2.0.0)
Requires-Dist: plac (>=1.3.5,<2.0.0)
Requires-Dist: polars (>=0.16.8,<0.17.0)
Requires-Dist: pysimplelog (>=4.0.0,<5.0.0)
